[
  {
    "punkte": 2,
    "inhalt_id": 612,
    "text": "Welche Schritte sind essenziell für die erfolgreiche Implementierung einer Lösung?",
    "version": 1,
    "nummer": 2,
    "antworten": [
      {
        "text": "Eine gründliche Planung der Umsetzungsschritte",
        "erklaerung": "Planung sorgt für eine strukturierte Implementierung.",
        "isKorrekt": true
      },
      {
        "text": "Das sofortige Anwenden ohne Tests",
        "erklaerung": "Tests sind wichtig, um Fehler zu vermeiden.",
        "isKorrekt": false
      },
      {
        "text": "Eine detaillierte Überwachung während der Implementierung",
        "erklaerung": "Überwachung stellt sicher, dass die Lösung korrekt umgesetzt wird.",
        "isKorrekt": true
      }
    ]
  },
  {
    "punkte": 3,
    "inhalt_id": 612,
    "text": "Warum ist die Überprüfung der Implementierung nach Abschluss wichtig?",
    "version": 1,
    "nummer": 2,
    "antworten": [
      {
        "text": "Um sicherzustellen, dass die Lösung wie beabsichtigt funktioniert",
        "erklaerung": "Eine abschließende Überprüfung zeigt, ob das Ziel erreicht wurde.",
        "isKorrekt": true
      },
      {
        "text": "Weil damit festgestellt werden kann, ob zusätzliche Maßnahmen nötig sind",
        "erklaerung": "Die Überprüfung deckt eventuelle Lücken oder Probleme auf.",
        "isKorrekt": true
      },
      {
        "text": "Um den Kunden sofort nach Implementierung zu informieren",
        "erklaerung": "Die Überprüfung ist primär für interne Qualitätskontrolle.",
        "isKorrekt": false
      }
    ]
  },
  {
    "punkte": 1,
    "inhalt_id": 612,
    "text": "Eine erfolgreiche Implementierung erfordert eine klare Planung und kontinuierliche Überwachung.",
    "version": 1,
    "nummer": 2,
    "antworten": [
      {
        "text": "richtig",
        "erklaerung": "Ohne Planung und Überwachung erhöht sich das Fehlerpotenzial.",
        "isKorrekt": true
      },
      {
        "text": "falsch",
        "erklaerung": "Ohne diese Maßnahmen wird die Implementierung riskant.",
        "isKorrekt": false
      }
    ]
  },
  {
    "punkte": 2,
    "inhalt_id": 612,
    "text": "Welche Maßnahmen unterstützen eine reibungslose Implementierung?",
    "version": 1,
    "nummer": 2,
    "antworten": [
      {
        "text": "Eine klare Kommunikation der Implementierungsschritte an das Team",
        "erklaerung": "Klare Kommunikation fördert das Verständnis und die Effizienz.",
        "isKorrekt": true
      },
      {
        "text": "Das spontane Anpassen der Implementierung ohne Rücksprache",
        "erklaerung": "Spontane Änderungen ohne Rücksprache können Probleme verursachen.",
        "isKorrekt": false
      },
      {
        "text": "Die Nutzung von Checklisten zur Überprüfung jedes Schrittes",
        "erklaerung": "Checklisten helfen, keine wichtigen Schritte zu übersehen.",
        "isKorrekt": true
      }
    ]
  },
  {
    "punkte": 3,
    "inhalt_id": 612,
    "text": "Welche Herausforderungen können während der Implementierung auftreten?",
    "version": 1,
    "nummer": 2,
    "antworten": [
      {
        "text": "Unerwartete technische Probleme, die zusätzliche Ressourcen erfordern",
        "erklaerung": "Unerwartete Probleme können den Implementierungsprozess verzögern.",
        "isKorrekt": true
      },
      {
        "text": "Ein Mangel an Kommunikation zwischen den beteiligten Teammitgliedern",
        "erklaerung": "Fehlende Kommunikation führt oft zu Missverständnissen und Verzögerungen.",
        "isKorrekt": true
      },
      {
        "text": "Die Möglichkeit, die Implementierung spontan ohne vorherige Planung anzupassen",
        "erklaerung": "Spontane Anpassungen ohne Planung können die Implementierung gefährden.",
        "isKorrekt": false
      }
    ]
  }
]
